Verilog_Examples/Basic/Multiplexer/mux821.v
module mux8to1(
    input [7:0] a,
    input [2:0] sel,
    output reg out
);

always @(*) 

begin
    case(sel)
        3'b000: out = a[0];
        3'b001: out = a[1];
        3'b010: out = a[2];
        3'b011: out = a[3];
        3'b100: out = a[4];
        3'b101: out = a[5];
        3'b110: out = a[6];
        3'b111: out = a[7];
        default: out = 1'b0;
    endcase
end

endmodule

Verilog_Examples/Basic/Multiplexer/mux81_tb.v
module mux81_tb;

reg  [7:0] a;
reg  [2:0] sel;
wire       out;

integer i;
integer errors;

mux8to1 m1 (
    .a(a),
    .sel(sel),
    .out(out)
);

initial begin
    $dumpfile("mux81_tb.vcd");
    $dumpvars(0, mux81_tb);

    errors = 0;

    // Test 1: Alternating pattern
    
    a = 8'b01010101;

    for (i = 0; i < 8; i = i + 1) begin
        sel = i;
        #10;

        if (out !== a[sel]) begin
            $display("FAIL: a=%b sel=%b expected=%b got=%b",
                     a, sel, a[sel], out);
            errors = errors + 1;
        end
        else begin
            $display("PASS: a=%b sel=%b out=%b",
                     a, sel, out);
        end
    end

    // Test 2: All ones
    a = 8'b11111111;

    for (i = 0; i < 8; i = i + 1) begin
        sel = i;
        #10;

        if (out !== a[sel]) begin
            $display("FAIL: a=%b sel=%b expected=%b got=%b",
                     a, sel, a[sel], out);
            errors = errors + 1;
        end
        else begin
            $display("PASS: a=%b sel=%b out=%b",
                     a, sel, out);
        end
    end

    // Test 3: All zeros
    a = 8'b00000000;

    for (i = 0; i < 8; i = i + 1) begin
        sel = i;
        #10;

        if (out !== a[sel]) begin
            $display("FAIL: a=%b sel=%b expected=%b got=%b",
                     a, sel, a[sel], out);
            errors = errors + 1;
        end
        else begin
            $display("PASS: a=%b sel=%b out=%b",
                     a, sel, out);
        end
    end

    // Test 4: Opposite alternating pattern
    a = 8'b10101010;

    for (i = 0; i < 8; i = i + 1) begin
        sel = i;
        #10;

        if (out !== a[sel]) begin
            $display("FAIL: a=%b sel=%b expected=%b got=%b",
                     a, sel, a[sel], out);
            errors = errors + 1;
        end
        else begin
            $display("PASS: a=%b sel=%b out=%b",
                     a, sel, out);
        end
    end

    // Final result
    if (errors == 0)
        $display("ALL TESTS PASSED");
    else
        $display("TEST FAILED: %0d errors", errors);

    $finish;
end

endmodule

Verilog_Examples/Basic/Multiplexer/mux81_tb.vcd
$date
	Sat Sep 19 23:37:01 2026
$end
$version
	Icarus Verilog
$end
$timescale
	1s
$end
$scope module mux81_tb $end
$var wire 1 ! out $end
$var reg 8 " a [7:0] $end
$var reg 3 # sel [2:0] $end
$var integer 32 $ errors [31:0] $end
$var integer 32 % i [31:0] $end
$scope module m1 $end
$var wire 8 & a [7:0] $end
$var wire 3 ' sel [2:0] $end
$var reg 1 ! out $end
$upscope $end
$upscope $end
$enddefinitions $end
$comment Show the parameter values. $end
$dumpall
$end
#0
$dumpvars
b0 '
b1010101 &
b0 %
b0 $
b0 #
b1010101 "
1!
$end
#10
0!
b1 #
b1 '
b1 %
#20
1!
b10 #
b10 '
b10 %
#30
0!
b11 #
b11 '
b11 %
#40
1!
b100 #
b100 '
b100 %
#50
0!
b101 #
b101 '
b101 %
#60
1!
b110 #
b110 '
b110 %
#70
0!
b111 #
b111 '
b111 %
#80
1!
b0 #
b0 '
b11111111 "
b11111111 &
b0 %
#90
b1 #
b1 '
b1 %
#100
b10 #
b10 '
b10 %
#110
b11 #
b11 '
b11 %
#120
b100 #
b100 '
b100 %
#130
b101 #
b101 '
b101 %
#140
b110 #
b110 '
b110 %
#150
b111 #
b111 '
b111 %
#160
0!
b0 #
b0 '
b0 "
b0 &
b0 %
#170
b1 #
b1 '
b1 %
#180
b10 #
b10 '
b10 %
#190
b11 #
b11 '
b11 %
#200
b100 #
b100 '
b100 %
#210
b101 #
b101 '
b101 %
#220
b110 #
b110 '
b110 %
#230
b111 #
b111 '
b111 %
#240
b0 #
b0 '
b10101010 "
b10101010 &
b0 %
#250
1!
b1 #
b1 '
b1 %
#260
0!
b10 #
b10 '
b10 %
#270
1!
b11 #
b11 '
b11 %
#280
0!
b100 #
b100 '
b100 %
#290
1!
b101 #
b101 '
b101 %
#300
0!
b110 #
b110 '
b110 %
#310
1!
b111 #
b111 '
b111 %
#320
b1000 %
